[
  {
    "id": 1,
    "title": "SELECT",
    "slug": "select"
  },
  {
    "id": 2,
    "title": "SELECT DISTINCT",
    "slug": "select_distinct"
  },
  {
    "id": 3,
    "title": "WHERE",
    "slug": "where"
  },
  {
    "id": 4,
    "title": "ORDER BY",
    "slug": "order_by"
  },
  {
    "id": 5,
    "title": "AND",
    "slug": "and"
  },
  {
    "id": 6,
    "title": "OR",
    "slug": "or"
  },
  {
    "id": 7,
    "title": "NOT",
    "slug": "not"
  },
  {
    "id": 8,
    "title": "INSERT",
    "slug": "insert"
  },
  {
    "id": 9,
    "title": "NULL VALUES",
    "slug": "null_values"
  },
  {
    "id": 10,
    "title": "UPDATE",
    "slug": "update"
  },
  {
    "id": 11,
    "title": "DELETE",
    "slug": "delete"
  },
  {
    "id": 12,
    "title": "MIN AND MAX",
    "slug": "min_and_max"
  },
  {
    "id": 13,
    "title": "COUNT",
    "slug": "count"
  },
  {
    "id": 14,
    "title": "SUM",
    "slug": "sum"
  },
  {
    "id": 15,
    "title": "AVG",
    "slug": "avg"
  },
  {
    "id": 16,
    "title": "LIKE",
    "slug": "like"
  },
  {
    "id": 17,
    "title": "WILDCARD",
    "slug": "wildcard"
  },
  {
    "id": 18,
    "title": "IN",
    "slug": "in"
  },
  {
    "id": 19,
    "title": "BETWEEN",
    "slug": "between"
  },
  {
    "id": 20,
    "title": "ALIASES",
    "slug": "aliases"
  },
  {
    "id": 21,
    "title": "OPERATOR PERBANDINGAN",
    "slug": "operator_perbandingan"
  },
  {
    "id": 22,
    "title": "OPERATOR ARITMATIKA",
    "slug": "operator_aritmatika"
  },
  {
    "id": 23,
    "title": "LIMIT",
    "slug": "limit"
  },
  {
    "id": 24,
    "title": "GROUP BY",
    "slug": "group_by"
  }
]
